setuptools_scm_custom/__init__.py
setuptools_scm_custom-0.1.0.dist-info/METADATA
setuptools_scm_custom-0.1.0.dist-info/WHEEL
setuptools_scm_custom-0.1.0.dist-info/top_level.txt
setuptools_scm_custom-0.1.0.dist-info/RECORD
