Metadata-Version: 2.1
Name: setuptools-scm-custom
Version: 0.1.0
Requires-Dist: setuptools >=64
Requires-Dist: setuptools-scm >=8
